{
  "title": "SSH - Contato imediato de primeiro grau",
  "description": "Conceitos básicos sobre o uso do SSH.",
  "details": {
    "intro": {
      "text": "intro.md",
      "background": "setup.sh"
    },
    "steps": [
      {
        "title": "O que é SSH e como funciona?",
        "text": "passo01/roteiro.md"
      },
      {
        "title": "Criando um par de chaves SSH",
        "text": "passo02/roteiro.md"
      },
      {
        "title": "Copiando a chave pública",
        "text": "passo03/roteiro.md"
      },
      {
        "title": "Executando comandos simples",
        "text": "passo04/roteiro.md"
      }
    ],
    "assets": {
      "controlplane": [
        { "file": "script01.sh", "target": "~/", "chmod": "+x" }
      ]
    }
  },
  "backend": {
    "imageid": "kubernetes-kubeadm-2nodes"
  }
}
